{
  "format_version": "1.8.0",
  "animations": {
    "animation.ufrn.waypoint": {
      "loop": true,
      "bones": {
        "root": {
          "rotation": [
            "query.rotation_to_camera(0)",
            "query.rotation_to_camera(1)",
            0
          ],
          "scale": ["variable.icon_scale", "variable.icon_scale", 1]
        }
      }
    },
    "animation.ufrn.waypoint.hidden": {
      "loop": true,
      "bones": {
        "root": {
          "scale": 0
        }
      }
    }
  }
}
